{"Runtime (seconds)":303.3403103351593,"GOOG Stock Price Prediction by iTransformer(no MSTL)":{"format":"png","width":1000,"height":600,"_type":"image-file","sha256":"e4a952bd795ebfa0dde1415aa63ddd4abfa159013bda2d44d203384476e44aaa","size":54683,"path":"media/images/GOOG Stock Price Prediction by iTransformer(no MSTL)_205_e4a952bd795ebfa0dde1.png"},"_runtime":6357.326742909,"predicted_stock_price":212.05209350585938,"rmse":24.912094116210938,"train_loss":0.06612189427046022,"valid_loss":0.03401090204715729,"_step":206,"dim":128,"_wandb":{"runtime":6357},"mae":24.912094116210938,"_timestamp":1.7390173355033233e+09,"depth":4,"r2_score":NaN,"real_stock_price":187.13999938964844,"mse":620.6124332549516}