{
    "2012-05-18_to_2024-11-25": {
        "dates": {
            "start_date": "2012-05-18",
            "end_date": "2024-11-25"
        },
        "trend": {
            "best_params": {
                "observation_period_num": 19,
                "train_rates": 0.8865836345834944,
                "learning_rate": 0.0007035502149094699,
                "batch_size": 174,
                "step_size": 3,
                "gamma": 0.9687105530681804
            }
        },
        "seasonal_0": {
            "best_params_0": {
                "observation_period_num": 14,
                "train_rates": 0.8619907904693898,
                "learning_rate": 0.0005056251732391923,
                "batch_size": 26,
                "step_size": 7,
                "gamma": 0.9556372879079656
            }
        },
        "seasonal_1": {
            "best_params_1": {
                "observation_period_num": 15,
                "train_rates": 0.8955277245460036,
                "learning_rate": 0.00023541136290421226,
                "batch_size": 17,
                "step_size": 10,
                "gamma": 0.8868269025868337
            }
        },
        "seasonal_2": {
            "best_params_2": {
                "observation_period_num": 21,
                "train_rates": 0.8651115400567491,
                "learning_rate": 4.7111530387288834e-05,
                "batch_size": 16,
                "step_size": 15,
                "gamma": 0.9124051179977172
            }
        },
        "seasonal_3": {
            "best_params_3": {
                "observation_period_num": 14,
                "train_rates": 0.8259306258055445,
                "learning_rate": 0.0007690831947589476,
                "batch_size": 31,
                "step_size": 5,
                "gamma": 0.7628710972372446
            }
        },
        "resid": {
            "best_params": {
                "observation_period_num": 18,
                "train_rates": 0.8592431822917379,
                "learning_rate": 0.0002417088405426852,
                "batch_size": 38,
                "step_size": 8,
                "gamma": 0.8153686380823975
            }
        }
    }
}