{
    "2012-05-18_to_2024-11-25": {
        "dates": {
            "start_date": "2012-05-18",
            "end_date": "2024-11-25"
        },
        "trend": {
            "best_params": {
                "observation_period_num": 5,
                "train_rates": 0.8066113564404266,
                "learning_rate": 0.000462769100818871,
                "batch_size": 74,
                "step_size": 5,
                "gamma": 0.9624949595038581
            }
        },
        "seasonal_0": {
            "best_params_0": {
                "observation_period_num": 5,
                "train_rates": 0.833003555552845,
                "learning_rate": 0.00011521760220635876,
                "batch_size": 75,
                "step_size": 12,
                "gamma": 0.8226047512653859
            }
        },
        "seasonal_1": {
            "best_params_1": {
                "observation_period_num": 15,
                "train_rates": 0.9383123444066815,
                "learning_rate": 0.0004694591913094869,
                "batch_size": 58,
                "step_size": 4,
                "gamma": 0.8603074228501688
            }
        },
        "seasonal_2": {
            "best_params_2": {
                "observation_period_num": 8,
                "train_rates": 0.9651148190175596,
                "learning_rate": 0.0009536241953108215,
                "batch_size": 87,
                "step_size": 15,
                "gamma": 0.8155769297215802
            }
        },
        "seasonal_3": {
            "best_params_3": {
                "observation_period_num": 15,
                "train_rates": 0.8942770281399419,
                "learning_rate": 7.956973552490178e-05,
                "batch_size": 32,
                "step_size": 7,
                "gamma": 0.9674011027032974
            }
        },
        "resid": {
            "best_params": {
                "observation_period_num": 10,
                "train_rates": 0.8958186370390298,
                "learning_rate": 0.0008213213002676373,
                "batch_size": 16,
                "step_size": 14,
                "gamma": 0.7676623930044139
            }
        }
    }
}