{"GOOG Stock Price Prediction by iTransformer(no MSTL)":{"height":600,"_type":"image-file","sha256":"d0aa41c3b9c3e8701a8acb26dc667a47d479ee124b2a61d3bd414624cc32df5f","size":55113,"path":"media/images/GOOG Stock Price Prediction by iTransformer(no MSTL)_301_d0aa41c3b9c3e8701a8a.png","format":"png","width":1000},"Runtime (seconds)":110.57859921455383,"valid_loss":0.03540434315800667,"train_loss":0.07210669375596479,"_step":302,"_timestamp":1.7389896179921436e+09,"mse":299.09584997803904,"rmse":17.294387817382812,"_runtime":2847.47596062,"real_stock_price":187.13999938964844,"r2_score":NaN,"_wandb":{"runtime":2847},"depth":4,"predicted_stock_price":204.43438720703125,"mae":17.294387817382812,"dim":128}