{"Runtime (seconds)":98.53213047981262,"_timestamp":1.7287584366880665e+09,"Train Loss (Resid)":0.016978234395247517,"_runtime":100.781622419,"_wandb":{"runtime":100},"Apple Stock Price Prediction":{"size":52190,"path":"media/images/Apple Stock Price Prediction_100_fb279b60cbf7ebe9c701.png","format":"png","width":1000,"height":600,"_type":"image-file","sha256":"fb279b60cbf7ebe9c7019a5852ad8a62bd493bf157e7dc36e2d9a4b889520166"},"Validation Loss (Seasonal)":0.0725325495004654,"_step":101,"Validation Loss (Resid)":0.04083799570798874,"Validation Loss (Trend)":0.01348840445280075,"Train Loss (Seasonal)":0.01279604672030969,"Train Loss (Trend)":0.011397434737194668}