{"AMZN Stock Price Prediction by Transformer(no MSTL)":{"height":600,"_type":"image-file","sha256":"be4999e0bb7f9c1c8269fa0354ac6565e8a5cbe01bcad5895aa01ccab20c81ec","size":51176,"path":"media/images/AMZN Stock Price Prediction by Transformer(no MSTL)_301_be4999e0bb7f9c1c8269.png","format":"png","width":1000},"predicted_stock_price":198.76222229003906,"depth":4,"rmse":34.16777038574219,"_runtime":8592.12971592,"mae":34.16777038574219,"Runtime (seconds)":150.6239881515503,"dim":128,"_wandb":{"runtime":8592},"mse":1167.4365331328008,"valid_loss":0.08662901818752289,"real_stock_price":232.92999267578125,"train_loss":0.08253920578123353,"_timestamp":1.736235303899872e+09,"_step":302,"r2_score":NaN}